bitbox02/__init__.py
bitbox02/py.typed
bitbox02/util.py
bitbox02/bitbox02/__init__.py
bitbox02/bitbox02/bitbox02.py
bitbox02/bitbox02/bootloader.py
bitbox02/bitbox02/py.typed
bitbox02/bitbox02/secp256k1.py
bitbox02/communication/__init__.py
bitbox02/communication/bitbox_api_protocol.py
bitbox02/communication/communication.py
bitbox02/communication/devices.py
bitbox02/communication/py.typed
bitbox02/communication/generated/__init__.py
bitbox02/communication/generated/antiklepto_pb2.py
bitbox02/communication/generated/backup_commands_pb2.py
bitbox02/communication/generated/backup_commands_pb2.pyi
bitbox02/communication/generated/bitbox02_system_pb2.py
bitbox02/communication/generated/bitbox02_system_pb2.pyi
bitbox02/communication/generated/bluetooth_pb2.py
bitbox02/communication/generated/btc_pb2.py
bitbox02/communication/generated/btc_pb2.pyi
bitbox02/communication/generated/cardano_pb2.py
bitbox02/communication/generated/common_pb2.py
bitbox02/communication/generated/common_pb2.pyi
bitbox02/communication/generated/eth_pb2.py
bitbox02/communication/generated/eth_pb2.pyi
bitbox02/communication/generated/hww_pb2.py
bitbox02/communication/generated/hww_pb2.pyi
bitbox02/communication/generated/keystore_pb2.py
bitbox02/communication/generated/keystore_pb2.pyi
bitbox02/communication/generated/mnemonic_pb2.py
bitbox02/communication/generated/mnemonic_pb2.pyi
bitbox02/communication/generated/perform_attestation_pb2.py
bitbox02/communication/generated/perform_attestation_pb2.pyi
bitbox02/communication/generated/system_pb2.py
bitbox02/communication/generated/system_pb2.pyi
bitbox02/communication/u2fhid/__init__.py
bitbox02/communication/u2fhid/u2fhid.py
bitbox02-7.0.0.dist-info/LICENSE
bitbox02-7.0.0.dist-info/METADATA
bitbox02-7.0.0.dist-info/WHEEL
bitbox02-7.0.0.dist-info/top_level.txt
bitbox02-7.0.0.dist-info/RECORD
