Metadata-Version: 2.1
Name: bitbox02
Version: 7.0.0
Summary: Python library for bitbox02 communication
Home-page: https://github.com/BitBoxSwiss/bitbox02-firmware
Author: Shift Crypto
Author-email: support@bitbox.swiss
Keywords: digitalbitbox BitBoxSwiss bitbox bitbox02 bitcoin litecoin ethereum erc20 u2f
Classifier: Intended Audience :: Developers
Classifier: License :: OSI Approved :: Apache Software License
Classifier: Programming Language :: Python :: 3.6
Requires-Python: >=3.6
License-File: LICENSE
Requires-Dist: base58 >=2.0.0
Requires-Dist: ecdsa >=0.14
Requires-Dist: hidapi >=0.14.0
Requires-Dist: noiseprotocol >=0.3
Requires-Dist: protobuf >=3.20
Requires-Dist: semver >=2.8.1
Requires-Dist: typing-extensions >=3.7.4
